alive_progress/__init__.py
alive_progress/animations/__init__.py
alive_progress/animations/bars.py
alive_progress/animations/spinner_compiler.py
alive_progress/animations/spinners.py
alive_progress/animations/utils.py
alive_progress/core/__init__.py
alive_progress/core/calibration.py
alive_progress/core/configuration.py
alive_progress/core/hook_manager.py
alive_progress/core/progress.py
alive_progress/styles/__init__.py
alive_progress/styles/exhibit.py
alive_progress/styles/internal.py
alive_progress/tools/__init__.py
alive_progress/tools/demo.py
alive_progress/tools/repl.py
alive_progress/tools/sampling.py
alive_progress/tools/unicode_breaks.py
alive_progress/tools/utils.py
alive_progress/utils/__init__.py
alive_progress/utils/cells.py
alive_progress/utils/colors.py
alive_progress/utils/timing.py
alive_progress/utils/terminal/__init__.py
alive_progress/utils/terminal/jupyter.py
alive_progress/utils/terminal/non_tty.py
alive_progress/utils/terminal/tty.py
alive_progress/utils/terminal/void.py
lebrunthibault_alive_progress-3.1.7.data/data/LICENSE
lebrunthibault_alive_progress-3.1.7.dist-info/LICENSE
lebrunthibault_alive_progress-3.1.7.dist-info/METADATA
lebrunthibault_alive_progress-3.1.7.dist-info/WHEEL
lebrunthibault_alive_progress-3.1.7.dist-info/top_level.txt
lebrunthibault_alive_progress-3.1.7.dist-info/RECORD
