Metadata-Version: 2.1
Name: lebrunthibault-alive-progress
Version: 3.1.7
Summary: A new kind of Progress Bar, with real-time throughput, ETA, and very cool animations!
Home-page: https://github.com/lebrunthibault/alive-progress
Author: Thibault Lebrun
Author-email: thibaultlebrun@live.fr
License: MIT
Keywords: progress,bar,progress-bar,progressbar,spinner,eta,monitoring,python,terminal,multi-threaded,REPL,alive,animated,visual,feedback,simple,live,efficient,monitor,stats,elapsed,time,throughput
Classifier: Development Status :: 5 - Production/Stable
Classifier: Intended Audience :: Developers
Classifier: Environment :: Console
Classifier: Natural Language :: English
Classifier: License :: OSI Approved :: MIT License
Classifier: Programming Language :: Python :: 3
Classifier: Programming Language :: Python :: 3.7
Classifier: Programming Language :: Python :: 3.8
Classifier: Programming Language :: Python :: 3.9
Classifier: Programming Language :: Python :: 3.10
Classifier: Programming Language :: Python :: 3.11
Requires-Python: >=3.7, <4
License-File: LICENSE
Requires-Dist: about-time ==4.2.1
Requires-Dist: grapheme ==0.6.0
